{"nodes":[
  
  {
    "Index":1,
    "Link":"http://www.appledaily.com.tw/realtimenews/article/new/20150521/614478/",
    "Date2":"20150521",
    "Title":"南韓首現MERS病例　3人確診64人遭隔離",
    "Like":34259,
    "pic_exist":"0",
    "Relate2":0.303853098739,
    "txtName":"apple174",
    "Branch":0,
    "Key1":"疫情",
    "Key2":"感染",
    "Key3":"病例",
    "Not":"1",
    "Relate":0.303853098739,
    "Datediff":380,
    "Dateindex":1
  },
  {
    "Index":2,
    "Link":"http://www.appledaily.com.tw/realtimenews/article/new/20150526/616896/",
    "Date2":"20150526",
    "Title":"韓新增第4起MERS確診病例　為前例患者女兒",
    "Like":3182,
    "pic_exist":"0",
    "Relate2":0.377112653312,
    "txtName":"apple208",
    "Branch":0,
    "Key1":"疫情",
    "Key2":"感染",
    "Key3":"病例",
    "Not":"1",
    "Relate":0.377112653312,
    "Datediff":385,
    "Dateindex":2
  },
  {
    "Index":3,
    "Link":"http://www.appledaily.com.tw/realtimenews/article/new/20150527/617640/",
    "Date2":"20150527",
    "Title":"韓國驚爆MERS　你不得不知的12大Q&A;",
    "Like":6079,
    "pic_exist":"1",
    "Relate2":0.608554980864,
    "txtName":"apple144",
    "Branch":0,
    "Key1":"疫情",
    "Key2":"感染",
    "Key3":"病例",
    "Not":"1",
    "Relate":0.608554980864,
    "Datediff":386,
    "Dateindex":3
  },
  {
    "Index":4,
    "Link":"http://www.appledaily.com.tw/realtimenews/article/new/20150528/618202/",
    "Date2":"20150528",
    "Title":"【更新】韓MERS疑似患者　前往中國出差",
    "Like":6178,
    "pic_exist":"1",
    "Relate2":0.341301075735,
    "txtName":"apple93",
    "Branch":1,
    "Key1":"患者",
    "Key2":"南韓",
    "Key3":"接受",
    "Not":"1",
    "Relate":0.2367490742,
    "Datediff":0,
    "Dateindex":4
  },
  {
    "Index":5,
    "Link":"http://www.appledaily.com.tw/realtimenews/article/new/20150529/618948/",
    "Date2":"20150529",
    "Title":"【更新】赴中出差韓男中MERS　確診患者達9人",
    "Like":2982,
    "pic_exist":"0",
    "Relate2":0.368105086916,
    "txtName":"apple171",
    "Branch":1,
    "Key1":"患者",
    "Key2":"南韓",
    "Key3":"接受",
    "Not":"1",
    "Relate":0.264582454867,
    "Datediff":1,
    "Dateindex":5
  },
  {
    "Index":6,
    "Link":"http://www.appledaily.com.tw/realtimenews/article/international/20150529/619445/",
    "Date2":"20150529",
    "Title":"再多2人確診　南韓MERS確診人數達12人",
    "Like":1212,
    "pic_exist":"1",
    "Relate2":0.304390388764,
    "txtName":"apple170",
    "Branch":4,
    "Key1":"確診",
    "Key2":"個案",
    "Key3":"綜合",
    "Not":"1",
    "Relate":0.285144864814,
    "Datediff":381,
    "Dateindex":5
  },
  {
    "Index":7,
    "Link":"http://www.appledaily.com.tw/appledaily/article/headline/20150529/36577667/",
    "Date2":"20150529",
    "Title":"韓MERS疫情暴走 發燒男入境中港",
    "Like":453,
    "pic_exist":"1",
    "Relate2":0.440123492204,
    "txtName":"apple130",
    "Branch":0,
    "Key1":"疫情",
    "Key2":"感染",
    "Key3":"病例",
    "Not":"1",
    "Relate":0.440123492204,
    "Datediff":388,
    "Dateindex":5
  },
  {
    "Index":8,
    "Link":"http://www.appledaily.com.tw/realtimenews/article/new/20150531/619941/",
    "Date2":"20150531",
    "Title":"南韓MERS確診患者　增至15人",
    "Like":1278,
    "pic_exist":"0",
    "Relate2":0.458717741299,
    "txtName":"apple82",
    "Branch":1,
    "Key1":"患者",
    "Key2":"南韓",
    "Key3":"接受",
    "Not":"1",
    "Relate":0.281109627877,
    "Datediff":3,
    "Dateindex":6
  },
  {
    "Index":9,
    "Link":"http://www.appledaily.com.tw/realtimenews/article/new/20150601/620712/",
    "Date2":"20150601",
    "Title":"【更新】韓國疑染MERS患者死亡　死因待確認",
    "Like":4997,
    "pic_exist":"0",
    "Relate2":0.32218993815,
    "txtName":"apple58",
    "Branch":1,
    "Key1":"患者",
    "Key2":"南韓",
    "Key3":"接受",
    "Not":"1",
    "Relate":0.254198969289,
    "Datediff":3,
    "Dateindex":7
  },
  {
    "Index":10,
    "Link":"http://www.appledaily.com.tw/realtimenews/article/new/20150601/620608/",
    "Date2":"20150601",
    "Title":"【更新】防MERS　疾管署派「假病人」測試醫師",
    "Like":3414,
    "pic_exist":"0",
    "Relate2":0.286888352212,
    "txtName":"apple186",
    "Branch":2,
    "Key1":"醫院",
    "Key2":"隔離",
    "Key3":"表示",
    "Not":"1",
    "Relate":0.212021039641,
    "Datediff":3,
    "Dateindex":7
  },
  {
    "Index":11,
    "Link":"http://www.appledaily.com.tw/appledaily/article/headline/20150601/36583016/",
    "Date2":"20150601",
    "Title":"MERS飆至15例 南韓道歉封鎖醫院",
    "Like":77,
    "pic_exist":"1",
    "Relate2":0.511795356676,
    "txtName":"apple88",
    "Branch":0,
    "Key1":"疫情",
    "Key2":"感染",
    "Key3":"病例",
    "Not":"1",
    "Relate":0.511795356676,
    "Datediff":390,
    "Dateindex":7
  },
  {
    "Index":12,
    "Link":"http://www.appledaily.com.tw/realtimenews/article/life/20150602/621228/",
    "Date2":"20150602",
    "Title":"【更新】韓MERS失控　台提高對首爾的旅遊警示",
    "Like":9204,
    "pic_exist":"1",
    "Relate2":0.287598849883,
    "txtName":"apple27",
    "Branch":3,
    "Key1":"韓國",
    "Key2":"旅遊",
    "Key3":"旅客",
    "Not":"1",
    "Relate":0.278268179271,
    "Datediff":0,
    "Dateindex":8
  },
  {
    "Index":13,
    "Link":"http://www.appledaily.com.tw/realtimenews/article/new/20150602/621000/",
    "Date2":"20150602",
    "Title":"【更新】MERS疫情擴大　疾管署：擬提高赴韓旅遊警示",
    "Like":269,
    "pic_exist":"1",
    "Relate2":0.338050622642,
    "txtName":"apple115",
    "Branch":3,
    "Key1":"韓國",
    "Key2":"旅遊",
    "Key3":"旅客",
    "Not":"1",
    "Relate":0.274570163265,
    "Datediff":0,
    "Dateindex":8
  },
  {
    "Index":14,
    "Link":"http://www.appledaily.com.tw/appledaily/article/headline/20150602/36584134/",
    "Date2":"20150602",
    "Title":"驚 韓首見MERS疑例死亡",
    "Like":72,
    "pic_exist":"1",
    "Relate2":0.516672006671,
    "txtName":"apple182",
    "Branch":0,
    "Key1":"疫情",
    "Key2":"感染",
    "Key3":"病例",
    "Not":"1",
    "Relate":0.516672006671,
    "Datediff":391,
    "Dateindex":8
  },
  {
    "Index":15,
    "Link":"http://www.appledaily.com.tw/realtimenews/article/new/20150603/622110/",
    "Date2":"20150603",
    "Title":"【更新】韓MERS疫情延燒　台灣旅客：沒在怕的",
    "Like":13046,
    "pic_exist":"1",
    "Relate2":0.133316534359,
    "txtName":"apple33",
    "Branch":3,
    "Key1":"韓國",
    "Key2":"旅遊",
    "Key3":"旅客",
    "Not":"1",
    "Relate":0.133316534359,
    "Datediff":1,
    "Dateindex":9
  },
  {
    "Index":16,
    "Link":"http://www.appledaily.com.tw/realtimenews/article/new/20150603/621714/",
    "Date2":"20150603",
    "Title":"MERS疫情突破首都圈　韓209所學校停課",
    "Like":6020,
    "pic_exist":"1",
    "Relate2":0.330183384688,
    "txtName":"apple41",
    "Branch":0,
    "Key1":"疫情",
    "Key2":"感染",
    "Key3":"病例",
    "Not":"1",
    "Relate":0.330183384688,
    "Datediff":392,
    "Dateindex":9
  },
  {
    "Index":17,
    "Link":"http://www.appledaily.com.tw/realtimenews/article/new/20150604/623016/",
    "Date2":"20150604",
    "Title":"失控？染MERS醫生趴趴走　接觸至少1500人",
    "Like":13638,
    "pic_exist":"1",
    "Relate2":0.29073762631,
    "txtName":"apple19",
    "Branch":0,
    "Key1":"疫情",
    "Key2":"感染",
    "Key3":"病例",
    "Not":"1",
    "Relate":0.29073762631,
    "Datediff":393,
    "Dateindex":10
  },
  {
    "Index":18,
    "Link":"http://www.appledaily.com.tw/realtimenews/article/new/20150604/622834/",
    "Date2":"20150604",
    "Title":"【更新】韓MERS出現第3起死亡病例　屬第3波感染",
    "Like":9770,
    "pic_exist":"0",
    "Relate2":0.298789646127,
    "txtName":"apple89",
    "Branch":0,
    "Key1":"疫情",
    "Key2":"感染",
    "Key3":"病例",
    "Not":"1",
    "Relate":0.298789646127,
    "Datediff":393,
    "Dateindex":10
  },
  {
    "Index":19,
    "Link":"http://www.appledaily.com.tw/realtimenews/article/new/20150604/622453/",
    "Date2":"20150604",
    "Title":"MERS疫情擴散韓軍也淪陷　1軍官檢體為陽性",
    "Like":4075,
    "pic_exist":"0",
    "Relate2":0.38188728957,
    "txtName":"apple99",
    "Branch":2,
    "Key1":"醫院",
    "Key2":"隔離",
    "Key3":"表示",
    "Not":"1",
    "Relate":0.277519990734,
    "Datediff":6,
    "Dateindex":10
  },
  {
    "Index":20,
    "Link":"http://www.appledaily.com.tw/appledaily/article/headline/20150605/36590753/",
    "Date2":"20150605",
    "Title":"韓醫染MERS 竟接觸1500人",
    "Like":7295,
    "pic_exist":"1",
    "Relate2":0.673298299806,
    "txtName":"apple59",
    "Branch":0,
    "Key1":"疫情",
    "Key2":"感染",
    "Key3":"病例",
    "Not":"1",
    "Relate":0.673298299806,
    "Datediff":394,
    "Dateindex":11
  },
  {
    "Index":21,
    "Link":"http://www.appledaily.com.tw/realtimenews/article/new/20150606/623854/",
    "Date2":"20150606",
    "Title":"韓MERS首例患者好轉　第2號患者痊癒出院",
    "Like":3328,
    "pic_exist":"0",
    "Relate2":0.143776672214,
    "txtName":"apple13",
    "Branch":1,
    "Key1":"患者",
    "Key2":"南韓",
    "Key3":"接受",
    "Not":"1",
    "Relate":0.143776672214,
    "Datediff":8,
    "Dateindex":12
  },
  {
    "Index":22,
    "Link":"http://www.appledaily.com.tw/realtimenews/article/new/20150606/623850/",
    "Date2":"20150606",
    "Title":"韓MERS再增9例　確診人數達50人",
    "Like":3173,
    "pic_exist":"0",
    "Relate2":0.38516444326,
    "txtName":"apple30",
    "Branch":4,
    "Key1":"確診",
    "Key2":"個案",
    "Key3":"綜合",
    "Not":"1",
    "Relate":0.242663755992,
    "Datediff":388,
    "Dateindex":12
  },
  {
    "Index":23,
    "Link":"http://www.appledaily.com.tw/realtimenews/article/new/20150607/624324/",
    "Date2":"20150607",
    "Title":"南韓公布24家MERS醫院　將一對一監控隔離者",
    "Like":1047,
    "pic_exist":"1",
    "Relate2":0.187889120798,
    "txtName":"apple18",
    "Branch":2,
    "Key1":"醫院",
    "Key2":"隔離",
    "Key3":"表示",
    "Not":"1",
    "Relate":0.187889120798,
    "Datediff":9,
    "Dateindex":13
  },
  {
    "Index":24,
    "Link":"http://www.appledaily.com.tw/realtimenews/article/new/20150607/624263/",
    "Date2":"20150607",
    "Title":"直擊南韓MERS源頭醫院　大門深鎖如鬼城",
    "Like":305,
    "pic_exist":"1",
    "Relate2":0.485640574438,
    "txtName":"apple1",
    "Branch":2,
    "Key1":"醫院",
    "Key2":"隔離",
    "Key3":"表示",
    "Not":"1",
    "Relate":0.241208055923,
    "Datediff":9,
    "Dateindex":13
  }
]
}